README.md
setup.cfg
setup.py
defunc/__init__.py
defunc/calibration.py
defunc/io.py
defunc/models.py
defunc/utils.py
defunc.egg-info/PKG-INFO
defunc.egg-info/SOURCES.txt
defunc.egg-info/dependency_links.txt
defunc.egg-info/requires.txt
defunc.egg-info/top_level.txt
defunc/data/alma_annual_50.amc
defunc/data/alma_atm_model.data