Metadata-Version: 1.0
Name: defunc
Version: 2019.07.08.1
Summary: Small package for De:code functions under development
Home-page: https://github.com/deshima-dev/defunc
Author: DESHIMA software team
Author-email: taniguchi@a.phys.nagoya-u.ac.jp
License: UNKNOWN
Platform: UNKNOWN
